granian/__init__.py
granian/__main__.py
granian/_compat.py
granian/_futures.py
granian/_granian.cpython-314-darwin.so
granian/_granian.pyi
granian/_imports.py
granian/_internal.py
granian/_loops.py
granian/_signals.py
granian/_types.py
granian/asgi.py
granian/cli.py
granian/constants.py
granian/errors.py
granian/http.py
granian/log.py
granian/net.py
granian/py.typed
granian/rsgi.py
granian/server/__init__.py
granian/server/common.py
granian/server/embed.py
granian/server/mp.py
granian/server/mt.py
granian/utils/__init__.py
granian/utils/proxies.py
granian/wsgi.py
granian-2.6.1.dist-info/METADATA
granian-2.6.1.dist-info/WHEEL
granian-2.6.1.dist-info/entry_points.txt
granian-2.6.1.dist-info/licenses/LICENSE
granian-2.6.1.dist-info/RECORD
