Metadata-Version: 2.4
Name: granian
Version: 2.6.1
Classifier: Development Status :: 5 - Production/Stable
Classifier: Intended Audience :: Developers
Classifier: License :: OSI Approved :: BSD License
Classifier: Operating System :: MacOS
Classifier: Operating System :: Microsoft :: Windows
Classifier: Operating System :: POSIX :: Linux
Classifier: Programming Language :: Python
Classifier: Programming Language :: Python :: 3
Classifier: Programming Language :: Python :: 3.10
Classifier: Programming Language :: Python :: 3.11
Classifier: Programming Language :: Python :: 3.12
Classifier: Programming Language :: Python :: 3.13
Classifier: Programming Language :: Python :: 3.14
Classifier: Programming Language :: Python :: Free Threading :: 2 - Beta
Classifier: Programming Language :: Python :: Implementation :: CPython
Classifier: Programming Language :: Python :: Implementation :: PyPy
Classifier: Programming Language :: Rust
Classifier: Topic :: Internet :: WWW/HTTP
Requires-Dist: click>=8.0.0
Requires-Dist: granian[dotenv,pname,reload] ; extra == 'all'
Requires-Dist: python-dotenv~=1.1 ; extra == 'dotenv'
Requires-Dist: setproctitle~=1.3.3 ; extra == 'pname'
Requires-Dist: watchfiles~=1.0 ; extra == 'reload'
Requires-Dist: rloop~=0.1 ; sys_platform != 'win32' and extra == 'rloop'
Requires-Dist: uvloop>=0.18.0 ; platform_python_implementation == 'CPython' and sys_platform != 'win32' and extra == 'uvloop'
Requires-Dist: winloop>=0.2.2 ; platform_python_implementation == 'CPython' and sys_platform == 'win32' and extra == 'winloop'
Provides-Extra: all
Provides-Extra: dotenv
Provides-Extra: pname
Provides-Extra: reload
Provides-Extra: rloop
Provides-Extra: uvloop
Provides-Extra: winloop
License-File: LICENSE
Summary: A Rust HTTP server for Python applications
Keywords: web,asyncio
Home-Page: https://github.com/emmett-framework/granian
Author-email: Giovanni Barillari <g@baro.dev>
License: BSD-3-Clause
Requires-Python: >=3.10
Project-URL: Funding, https://github.com/sponsors/gi0baro
Project-URL: Homepage, https://github.com/emmett-framework/granian
Project-URL: Source, https://github.com/emmett-framework/granian
